sage_utils/__init__.py
sage_utils/constants.py
sage_utils/extension.py
sage_utils/wrappers.py
sage_utils/amqp/__init__.py
sage_utils/amqp/base.py
sage_utils/amqp/clients.py
sage_utils/amqp/extension.py
sage_utils/amqp/mixins.py
sage_utils/amqp/workers.py
sage_utils-0.5.6.dist-info/METADATA
sage_utils-0.5.6.dist-info/RECORD
sage_utils-0.5.6.dist-info/WHEEL
sage_utils-0.5.6.dist-info/top_level.txt
