Metadata-Version: 2.1
Name: sage-utils
Version: 0.5.6
Summary: SDK for Open Matchmaking microservices in Python
Home-page: https://github.com/OpenMatchmaking/sage-utils-python
Author: Valeryi Savich
Author-email: relrin78@gmail.com
License: BSD
Platform: any
Classifier: License :: OSI Approved :: BSD License
Classifier: Intended Audience :: Developers
Classifier: Programming Language :: Python
Classifier: Programming Language :: Python :: 3
Classifier: Topic :: Internet :: WWW/HTTP
Requires-Dist: aioamqp (==0.12.0)
